agui_adk_endpoint/__init__.py
agui_adk_endpoint/endpoint.py
agui_adk_endpoint/factory.py
agui_adk_endpoint/utils.py
agui_adk_endpoint/validator.py
agui_adk_endpoint/webserver.py
agui_adk_endpoint-0.0.7.dist-info/WHEEL
agui_adk_endpoint-0.0.7.dist-info/entry_points.txt
agui_adk_endpoint-0.0.7.dist-info/METADATA
agui_adk_endpoint-0.0.7.dist-info/RECORD
