Metadata-Version: 2.3
Name: agui-adk-endpoint
Version: 0.0.7
Summary: AGUI ADK Endpoint
Author: Bruce Li
Author-email: Bruce Li <jiangwlee@163.com>
Requires-Dist: ag-ui-adk>=0.3.4
Requires-Dist: google-adk>=1.18.0
Requires-Python: >=3.12
